gcm/__init__.py
gcm/gcm.py
gcm/ray_gcm.py
gcm/ray_sparse_gcm.py
gcm/sparse_gcm.py
gcm/util.py
gcm/edge_selectors/__init__.py
gcm/edge_selectors/dense.py
gcm/edge_selectors/distance.py
gcm/edge_selectors/learned.py
gcm/edge_selectors/self_edge.py
gcm/edge_selectors/temporal.py
graph_conv_memory-0.0.7.dist-info/METADATA
graph_conv_memory-0.0.7.dist-info/WHEEL
graph_conv_memory-0.0.7.dist-info/top_level.txt
graph_conv_memory-0.0.7.dist-info/RECORD
