Metadata-Version: 2.1
Name: graph-conv-memory
Version: 0.0.7
Summary: Graph convolutional memory for reinforcement learning
Home-page: https://github.com/smorad/graph-conv-memory
Author: Steven Morad
Author-email: stevenmorad@gmail.com
License: UNKNOWN
Project-URL: Bug Tracker, https://github.com/smorad/graph-conv-memory/issues
Platform: UNKNOWN
Classifier: Programming Language :: Python :: 3
Classifier: License :: OSI Approved :: MIT License
Classifier: Operating System :: OS Independent
Requires-Python: >=3.6
Requires-Dist: torch
Requires-Dist: torch-geometric (>=1.7.0)
Requires-Dist: sparsemax
Requires-Dist: torchtyping
